cryptkeeper/__init__.py
cryptkeeper/constants.py
cryptkeeper/cryptkeeper.py
cryptkeeper/dependency_wrappers.py
cryptkeeper/export.py
cryptkeeper/helpers.py
cryptkeeper/orf_predict.py
cryptkeeper/plot.py
cryptkeeper/assets/cryptkeeper_long.svg
cryptkeeper/assets/favicon.svg
cryptkeeper/assets/html_template.html
cryptkeeper/assets/stylesheet.css
cryptkeeper-1.0.1.dist-info/LICENSE
cryptkeeper-1.0.1.dist-info/METADATA
cryptkeeper-1.0.1.dist-info/WHEEL
cryptkeeper-1.0.1.dist-info/entry_points.txt
cryptkeeper-1.0.1.dist-info/top_level.txt
cryptkeeper-1.0.1.dist-info/RECORD
